stressapi/__init__.py
stressapi/cli/__init__.py
stressapi/cli/main.py
stressapi-0.0.1.dist-info/LICENSE
stressapi-0.0.1.dist-info/METADATA
stressapi-0.0.1.dist-info/WHEEL
stressapi-0.0.1.dist-info/entry_points.txt
stressapi-0.0.1.dist-info/top_level.txt
stressapi-0.0.1.dist-info/RECORD
