Metadata-Version: 2.1
Name: stressapi
Version: 0.0.1
Summary: Use python to write an api interface stress test tool
Home-page: https://github.com/ponponon/stressapi
Author: ponponon
Author-email: 1729303158@qq.com
Maintainer: ponponon
Maintainer-email: 1729303158@qq.com
License: MIT License
Platform: all
Classifier: Programming Language :: Python
Classifier: Operating System :: MacOS :: MacOS X
Classifier: Operating System :: POSIX
Classifier: Programming Language :: Python :: 3
Classifier: Programming Language :: Python :: 3.8
Classifier: Programming Language :: Python :: 3.9
Classifier: Programming Language :: Python :: 3.10
Classifier: Programming Language :: Python :: 3.11
Classifier: Topic :: Internet
Classifier: Topic :: Software Development :: Libraries :: Python Modules
Classifier: Intended Audience :: Developers
License-File: LICENSE
Requires-Dist: click
Requires-Dist: requests
